nucleofind-1.2.3.dist-info/WHEEL
nucleofind-1.2.3.dist-info/entry_points.txt
nucleofind-1.2.3.dist-info/METADATA
nucleofind-1.2.3.dist-info/RECORD
nucleofind/logs.py
nucleofind/__version__.py
nucleofind/nautilus_module.cpython-310-x86_64-linux-gnu.so
nucleofind/build.py
nucleofind/install.py
nucleofind/__init__.py
nucleofind/clean.py
nucleofind/data/database.cif
nucleofind/data/__init__.py
nucleofind/prediction/save.py
nucleofind/prediction/util.py
nucleofind/prediction/arguments.py
nucleofind/prediction/grid_tools.py
nucleofind/prediction/predict.py
nucleofind/prediction/load.py
nucleofind/prediction/model.py
nucleofind/prediction/config.py
nucleofind/prediction/__init__.py
nucleofind/prediction/errors.py
lib/librfftw.a
lib/libccp4.a
lib/libclipper-core.a
lib/libfftw.a
lib/libclipper-cif.a
lib/libfftw3f_threads.a
lib/libclipper-contrib.a
lib/libclipper-cns.a
lib/libclipper-gemmi.a
lib/libclipper-minimol.a
lib/libmmdb2.a
lib/libclipper-mmdb.a
lib/libfftw3f.a
lib/libgemmi_cpp.a
lib/libclipper-ccp4.a
lib/pkgconfig/fftw3f.pc
lib/cmake/fftw3/FFTW3Targets.cmake
lib/cmake/fftw3/FFTW3Targets-release.cmake
lib/cmake/fftw3f/FFTW3LibraryDepends-release.cmake
lib/cmake/fftw3f/FFTW3LibraryDepends.cmake
lib/cmake/fftw3f/FFTW3fConfig.cmake
lib/cmake/fftw3f/FFTW3fConfigVersion.cmake
include/fftw3.h
include/gemmi/neighbor.hpp
include/gemmi/neutron92.hpp
include/gemmi/chemcomp.hpp
include/gemmi/json.hpp
include/gemmi/binner.hpp
include/gemmi/math.hpp
include/gemmi/fail.hpp
include/gemmi/bond_idx.hpp
include/gemmi/cifdoc.hpp
include/gemmi/c4322.hpp
include/gemmi/atox.hpp
include/gemmi/iterator.hpp
include/gemmi/monlib.hpp
include/gemmi/seqalign.hpp
include/gemmi/dirwalk.hpp
include/gemmi/modify.hpp
include/gemmi/mmcif.hpp
include/gemmi/interop.hpp
include/gemmi/fileutil.hpp
include/gemmi/contact.hpp
include/gemmi/mtz.hpp
include/gemmi/unitcell.hpp
include/gemmi/assembly.hpp
include/gemmi/sfcalc.hpp
include/gemmi/addends.hpp
include/gemmi/xds2mtz.hpp
include/gemmi/recgrid.hpp
include/gemmi/ddl.hpp
include/gemmi/seqid.hpp
include/gemmi/refln.hpp
