Metadata-Version: 2.1
Name: nucleofind
Version: 1.2.3
Summary: NucleoFind: A Deep-Learning Network for Interpreting Nucleic Acid Electron Density
Author-Email: Jordan Dialpuri <jordan.dialpuri@york.ac.uk>
Classifier: License :: OSI Approved :: BSD License
Project-URL: Homepage, https://github.com/Dialpuri/NucleoFind
Requires-Python: >=3.10
Requires-Dist: onnxruntime-gpu; platform_system != "Darwin"
Requires-Dist: onnxruntime; platform_system == "Darwin"
Requires-Dist: tqdm
Requires-Dist: gemmi
Requires-Dist: numpy
Requires-Dist: requests
